contextual/__init__.py
contextual/agent/__init__.py
contextual/agent/py.typed
contextual/agent/components/__init__.py
contextual/agent/components/base/__init__.py
contextual/agent/components/base/adk_a_agent.py
contextual/agent/components/base/adk_b_agent.py
contextual/agent/components/base/base.py
contextual/agent/components/prompts/__init__.py
contextual/agent/components/prompts/base.py
contextual/agent/components/prompts/test_a_prompt.py
contextual/agent/components/prompts/test_b_prompt.py
contextual/agent/components/prompts/test_seq_prompt.py
contextual/agent/components/sequential/__init__.py
contextual/agent/components/sequential/adk_sequential_agent.py
contextual/agent/factories/__init__.py
contextual/agent/factories/llm_factory.py
contextual/agent/managers/__init__.py
contextual/agent/managers/adk_manager.py
contextual/agent/managers/adk_seq_manager.py
contextual/agent/managers/base.py
contextual/agent/models/__init__.py
contextual/agent/models/content.py
contextual/agent/models/llm_model.py
contextual/agent/utils/__init__.py
contextual_studio_ai_agent-0.1.0.dist-info/licenses/LICENSE
contextual_studio_ai_agent-0.1.0.dist-info/METADATA
contextual_studio_ai_agent-0.1.0.dist-info/WHEEL
contextual_studio_ai_agent-0.1.0.dist-info/top_level.txt
contextual_studio_ai_agent-0.1.0.dist-info/RECORD
