Metadata-Version: 2.4
Name: contextual-studio-ai-agent
Version: 0.1.0
Summary: IA Generative Agent library to create autonomous agents using LLMs.
Author-email: Jorge Resino <jorgeresino143@gmail.com>
Maintainer-email: Jorge Resino <jorgeresino143@gmail.com>
License: MIT
Project-URL: Homepage, https://contextualstudio.com/
Project-URL: Documentation, https://github.com/contextual-studio/agent
Project-URL: Repository, https://github.com/contextual-studio/agent
Classifier: Development Status :: 4 - Beta
Classifier: Intended Audience :: Developers
Classifier: Topic :: Software Development :: Build Tools
Classifier: Programming Language :: Python :: 3.12
Requires-Python: >=3.12
License-File: LICENSE
Requires-Dist: dotenv==0.9.9
Requires-Dist: google-adk==1.16.0
Requires-Dist: litellm==1.78.6
Requires-Dist: loguru==0.7.3
Requires-Dist: pre-commit==4.3.0
Requires-Dist: pydantic==2.12.3
Requires-Dist: pytest==8.4.2
Dynamic: license-file
